datapackage_to_datasette/__init__.py
datapackage_to_datasette/cli.py
datapackage_to_datasette/utils.py
datapackage_to_datasette-0.4.1.dist-info/METADATA
datapackage_to_datasette-0.4.1.dist-info/WHEEL
datapackage_to_datasette-0.4.1.dist-info/entry_points.txt
datapackage_to_datasette-0.4.1.dist-info/licenses/LICENSE
datapackage_to_datasette-0.4.1.dist-info/RECORD
