Metadata-Version: 2.4
Name: datapackage-to-datasette
Version: 0.4.1
Summary: Import Frictionless Data Datapackages into SQLite and generate Datasette metadata
License-Expression: MIT
License-File: LICENSE
Author: chris48s
Requires-Python: >=3.10
Classifier: Framework :: Datasette
Requires-Dist: deepmerge (>=1.0.1,<3.0.0)
Requires-Dist: frictionless[sql] (>=5,<6)
Project-URL: Home, https://github.com/chris48s/datapackage-to-datasette
Project-URL: Source, https://github.com/chris48s/datapackage-to-datasette
